README.md
setup.py
HaoyunUse/__init__.py
HaoyunUse/use.py
HaoyunUse.egg-info/PKG-INFO
HaoyunUse.egg-info/SOURCES.txt
HaoyunUse.egg-info/dependency_links.txt
HaoyunUse.egg-info/top_level.txt